TempEmail/TempEmail.py
TempEmail/__init__.py
tempmail_py-1.0.dist-info/LICENSE
tempmail_py-1.0.dist-info/METADATA
tempmail_py-1.0.dist-info/WHEEL
tempmail_py-1.0.dist-info/top_level.txt
tempmail_py-1.0.dist-info/RECORD
