Metadata-Version: 2.1
Name: tempmail-py
Version: 1.0
Summary: Generate Temp Email and get messages of generated email and use in your projects
Home-page: https://github.com/zohaib3249
Author: Zohaib Yousaf
Author-email: zohaib3249@gmail.com
Project-URL: Bug Tracker, https://github.com/pypa/sampleproject/issues
Classifier: Programming Language :: Python :: 3
Classifier: License :: OSI Approved :: MIT License
Classifier: Operating System :: OS Independent
Requires-Python: >=3.8
License-File: LICENSE
